flask_dataapi/__init__.py
flask_dataapi/py.typed
flask_dataapi-0.2.1.dist-info/COPYING
flask_dataapi-0.2.1.dist-info/METADATA
flask_dataapi-0.2.1.dist-info/WHEEL
flask_dataapi-0.2.1.dist-info/top_level.txt
flask_dataapi-0.2.1.dist-info/RECORD
